LICENSE
README.md
setup.py
kclvm/__init__.py
kclvm/__main__.py
kclvm.egg-info/PKG-INFO
kclvm.egg-info/SOURCES.txt
kclvm.egg-info/dependency_links.txt
kclvm.egg-info/requires.txt
kclvm.egg-info/top_level.txt
kclvm.egg-info/zip-safe
kclvm/api/__init__.py
kclvm/api/object/__init__.py
kclvm/api/object/bytecode.py
kclvm/api/object/decorator.py
kclvm/api/object/function.py
kclvm/api/object/object.py
kclvm/api/object/schema.py
kclvm/api/object/internal/__init__.py
kclvm/api/object/internal/common.py
kclvm/api/object/internal/decorators.py
kclvm/api/object/internal/option.py
kclvm/api/object/internal/path_selector.py
kclvm/api/object/internal/selector.py
kclvm/api/object/internal/undefined.py
kclvm/api/version/__init__.py
kclvm/api/version/__main__.py
kclvm/api/version/checksum.txt
kclvm/api/version/version.py
kclvm/compiler/__init__.py
kclvm/compiler/astutil/__init__.py
kclvm/compiler/astutil/builder.py
kclvm/compiler/astutil/filter.py
kclvm/compiler/astutil/fix.py
kclvm/compiler/build/__init__.py
kclvm/compiler/build/compiler.py
kclvm/compiler/build/data.py
kclvm/compiler/build/preprocess.py
kclvm/compiler/build/symtable.py
kclvm/compiler/build/utils/__init__.py
kclvm/compiler/build/utils/units.py
kclvm/compiler/check/__init__.py
kclvm/compiler/check/check_type/__init__.py
kclvm/compiler/check/check_type/check_type.py
kclvm/compiler/extension/__init__.py
kclvm/compiler/extension/builtin/__init__.py
kclvm/compiler/extension/builtin/builtin.py
kclvm/compiler/extension/builtin/system_module/__init__.py
kclvm/compiler/extension/builtin/system_module/base64.py
kclvm/compiler/extension/builtin/system_module/collection.py
kclvm/compiler/extension/builtin/system_module/crypto.py
kclvm/compiler/extension/builtin/system_module/datetime.py
kclvm/compiler/extension/builtin/system_module/json.py
kclvm/compiler/extension/builtin/system_module/manifests.py
kclvm/compiler/extension/builtin/system_module/math.py
kclvm/compiler/extension/builtin/system_module/net.py
kclvm/compiler/extension/builtin/system_module/regex.py
kclvm/compiler/extension/builtin/system_module/testing.py
kclvm/compiler/extension/builtin/system_module/units.py
