Metadata-Version: 2.1
Name: kclvm
Version: 0.8.5
Summary: KCL Python SDK
Home-page: https://kcl-lang.io/
Author: KCL Authors
Author-email: 
License: Apache License 2.0
Platform: UNKNOWN
Requires-Python: >=3.7
License-File: LICENSE
